[
    {
        "filter":"14995377",
        "id":2819375,
        "opened":true,
        "type":2
    },
    {
        "filter":"^\u597d\u751c.*",
        "id":8505172,
        "opened":true,
        "type":1
    },
    {
        "filter":"\u9ec4\u65ed\u4e1c",
        "id":2285263,
        "opened":true,
        "type":0
    },
    {
        "filter":"\u9739\u96f3",
        "id":2762372,
        "opened":true,
        "type":0
    },
    {
        "filter":"\u7d20\u8fd8\u771f",
        "id":2762374,
        "opened":true,
        "type":0
    },
    {
        "filter":"\u554a\u554a",
        "id":2806237,
        "opened":true,
        "type":0
    },
    {
        "filter":"\u54c8\u54c8",
        "id":2806802,
        "opened":true,
        "type":0
    },
    {
        "filter":"\u90aa\u738b\u771f\u773c\u662f\u6700\u5f3a",
        "id":2911458,
        "opened":true,
        "type":0
    },
    {
        "filter":"\u4f1a\u5458",
        "id":3005281,
        "opened":true,
        "type":0
    },
    {
        "filter":"\u5fae\u7b11",
        "id":3005282,
        "opened":true,
        "type":0
    },
    {
        "filter":"\u5f39\u5e55",
        "id":4648012,
        "opened":true,
        "type":0
    },
    {
        "filter":"\u706b\u94b3\u5218\u660e",
        "id":6534957,
        "opened":true,
        "type":0
    },
    {
        "filter":".*\u827e\u5c14\u767b\u6cd5\u73af.*",
        "id":8282658,
        "opened":true,
        "type":0
    },
    {
        "filter":"^\u70ed.{1,2}\\S*",
        "id":6534836,
        "opened":true,
        "type":1
    },
    {
        "filter":"^(.+)?(\u554a){2,}(.+)?\\S*",
        "id":6534944,
        "opened":true,
        "type":1
    },
    {
        "filter":"(.)\\1{3,}",
        "id":6534999,
        "opened":true,
        "type":1
    },
    {
        "filter":"(.)\\1{2,}",
        "id":6535009,
        "opened":true,
        "type":1
    },
    {
        "filter":"^[\u79d2,\u5999,\u5973\u5c11].{0,4}",
        "id":6563618,
        "opened":true,
        "type":1
    },
    {
        "filter":".{2,3}\u725b[\u903c,\u58c1]S*",
        "id":6563625,
        "opened":true,
        "type":1
    },
    {
        "filter":"06f4ee4f",
        "id":1660897,
        "opened":true,
        "type":2
    },
    {
        "filter":"5e715d64",
        "id":1660899,
        "opened":true,
        "type":2
    },
    {
        "filter":"5735d866",
        "id":1660900,
        "opened":true,
        "type":2
    },
    {
        "filter":"4bb5466a",
        "id":1660901,
        "opened":true,
        "type":2
    },
    {
        "filter":"bd69eed0",
        "id":1662704,
        "opened":true,
        "type":2
    },
    {
        "filter":"48220c47",
        "id":1663123,
        "opened":true,
        "type":2
    },
    {
        "filter":"7f9c6002",
        "id":1664126,
        "opened":true,
        "type":2
    },
    {
        "filter":"c1094d09",
        "id":1664127,
        "opened":true,
        "type":2
    },
    {
        "filter":"095f923e",
        "id":2285262,
        "opened":true,
        "type":2
    },
    {
        "filter":"adb74961",
        "id":2762396,
        "opened":true,
        "type":2
    },
    {
        "filter":"7b5ebc26",
        "id":2764675,
        "opened":true,
        "type":2
    },
    {
        "filter":"7933bc6b",
        "id":2764676,
        "opened":true,
        "type":2
    },
    {
        "filter":"4a965e99",
        "id":2764677,
        "opened":true,
        "type":2
    },
    {
        "filter":"3720bdda",
        "id":2764678,
        "opened":true,
        "type":2
    },
    {
        "filter":"ad9e0c4d",
        "id":2806232,
        "opened":true,
        "type":2
    },
    {
        "filter":"2e70195f",
        "id":2806233,
        "opened":true,
        "type":2
    },
    {
        "filter":"644a65f9",
        "id":2806239,
        "opened":true,
        "type":2
    },
    {
        "filter":"220fda24",
        "id":2806251,
        "opened":true,
        "type":2
    },
    {
        "filter":"222e00d1",
        "id":2806259,
        "opened":true,
        "type":2
    },
    {
        "filter":"4ef71ff5",
        "id":2806265,
        "opened":true,
        "type":2
    },
    {
        "filter":"e02ff689",
        "id":2806266,
        "opened":true,
        "type":2
    },
    {
        "filter":"9b7cb11d",
        "id":2806291,
        "opened":true,
        "type":2
    },
    {
        "filter":"8f23a711",
        "id":2806292,
        "opened":true,
        "type":2
    },
    {
        "filter":"ed08d99a",
        "id":2806302,
        "opened":true,
        "type":2
    },
    {
        "filter":"9adf4b48",
        "id":2806330,
        "opened":true,
        "type":2
    },
    {
        "filter":"3e07a51",
        "id":2806337,
        "opened":true,
        "type":2
    },
    {
        "filter":"586836fc",
        "id":2832481,
        "opened":true,
        "type":2
    },
    {
        "filter":"4b4f5d0a",
        "id":2832482,
        "opened":true,
        "type":2
    },
    {
        "filter":"a3784e0d",
        "id":2832484,
        "opened":true,
        "type":2
    },
    {
        "filter":"f10ad850",
        "id":2899866,
        "opened":true,
        "type":2
    },
    {
        "filter":"734f35b9",
        "id":2899867,
        "opened":true,
        "type":2
    },
    {
        "filter":"8e21484a",
        "id":2899868,
        "opened":true,
        "type":2
    },
    {
        "filter":"5c87e9b6",
        "id":2899869,
        "opened":true,
        "type":2
    },
    {
        "filter":"64e99f5d",
        "id":2899870,
        "opened":true,
        "type":2
    },
    {
        "filter":"2d7d8894",
        "id":2899871,
        "opened":true,
        "type":2
    },
    {
        "filter":"9a907e81",
        "id":2899873,
        "opened":true,
        "type":2
    },
    {
        "filter":"7269c55d",
        "id":2911454,
        "opened":true,
        "type":2
    },
    {
        "filter":"3ba1bab0",
        "id":2913692,
        "opened":true,
        "type":2
    },
    {
        "filter":"6f14c171",
        "id":2913695,
        "opened":true,
        "type":2
    },
    {
        "filter":"f77fa21b",
        "id":2913696,
        "opened":true,
        "type":2
    },
    {
        "filter":"e6172972",
        "id":2913700,
        "opened":true,
        "type":2
    },
    {
        "filter":"d5077b49",
        "id":2913701,
        "opened":true,
        "type":2
    },
    {
        "filter":"4388fea0",
        "id":2913703,
        "opened":true,
        "type":2
    },
    {
        "filter":"933d7ae4",
        "id":2913704,
        "opened":true,
        "type":2
    },
    {
        "filter":"96424d53",
        "id":2913705,
        "opened":true,
        "type":2
    },
    {
        "filter":"d472bfa",
        "id":2913706,
        "opened":true,
        "type":2
    },
    {
        "filter":"430ef943",
        "id":2913707,
        "opened":true,
        "type":2
    },
    {
        "filter":"a8f8b1f7",
        "id":2913861,
        "opened":true,
        "type":2
    },
    {
        "filter":"ab969d63",
        "id":2922217,
        "opened":true,
        "type":2
    },
    {
        "filter":"7a9f4d12",
        "id":2940538,
        "opened":true,
        "type":2
    },
    {
        "filter":"95cd0652",
        "id":2940588,
        "opened":true,
        "type":2
    },
    {
        "filter":"d396b32b",
        "id":2969365,
        "opened":true,
        "type":2
    },
    {
        "filter":"48d97d8",
        "id":3005277,
        "opened":true,
        "type":2
    },
    {
        "filter":"1798adbf",
        "id":3012140,
        "opened":true,
        "type":2
    },
    {
        "filter":"c72aad67",
        "id":3012141,
        "opened":true,
        "type":2
    },
    {
        "filter":"4c7c428c",
        "id":3012144,
        "opened":true,
        "type":2
    },
    {
        "filter":"f4e8b2fb",
        "id":3221795,
        "opened":true,
        "type":2
    },
    {
        "filter":"232d78c",
        "id":3474629,
        "opened":true,
        "type":2
    },
    {
        "filter":"498501bd",
        "id":3474630,
        "opened":true,
        "type":2
    },
    {
        "filter":"c0c4b9e9",
        "id":3499124,
        "opened":true,
        "type":2
    },
    {
        "filter":"69edd969",
        "id":3499125,
        "opened":true,
        "type":2
    },
    {
        "filter":"f97eaa01",
        "id":4703806,
        "opened":true,
        "type":2
    },
    {
        "filter":"545505b",
        "id":5800495,
        "opened":true,
        "type":2
    },
    {
        "filter":"b4b4d6ac",
        "id":5816723,
        "opened":true,
        "type":2
    },
    {
        "filter":"e68b805d",
        "id":5816724,
        "opened":true,
        "type":2
    },
    {
        "filter":"72ce63ad",
        "id":5816725,
        "opened":true,
        "type":2
    },
    {
        "filter":"c1a4f758",
        "id":6013673,
        "opened":true,
        "type":2
    },
    {
        "filter":"c26edb1c",
        "id":6299232,
        "opened":true,
        "type":2
    },
    {
        "filter":".*\u597d\u751c\u54e6$",
        "id":8505175,
        "opened":true,
        "type":1
    },
    {
        "filter":"\u751c\u6b7b\u6211\u4e86",
        "id":8505176,
        "opened":true,
        "type":0
    },
    {
        "filter":"\u751c\u5230\u6389\u7259\u4e86",
        "id":8505182,
        "opened":true,
        "type":0
    },
    {
        "filter":"\u751c\u70b8\u4e86",
        "id":8505184,
        "opened":true,
        "type":0
    },
    {
        "filter":"^\u545c\u545c.*",
        "id":8505187,
        "opened":true,
        "type":1
    },
    {
        "filter":".*!",
        "id":8505192,
        "opened":true,
        "type":1
    },
    {
        "filter":".*\uff01",
        "id":8505202,
        "opened":true,
        "type":1
    },
    {
        "filter":"7577af54",
        "id":8505205,
        "opened":true,
        "type":2
    },
    {
        "filter":".*\u60f3\u54ed\u554a.*",
        "id":8505210,
        "opened":true,
        "type":1
    },
    {
        "filter":"^\u8d85\u751c$",
        "id":8505213,
        "opened":true,
        "type":1
    },
    {
        "filter":"^\u7ec8\u4e8e(\u554a|\u5230\u4e86){0,1}$",
        "id":8505231,
        "opened":true,
        "type":1
    },
    {
        "filter":"^\u597d(\u8036|\u5440|\u54e6|\u4e5f|\u6b38){0,1}$",
        "id":8505241,
        "opened":true,
        "type":1
    },
    {
        "filter":"^\u6765(\u4e86|\u54af|)$",
        "id":0,
        "opened":true,
        "type":1
    },
    {
        "filter":"\u5662\u8036",
        "id":8505250,
        "opened":true,
        "type":0
    },
    {
        "filter":"\u6b27\u8036",
        "id":8505256,
        "opened":true,
        "type":0
    },
    {
        "filter":"\u89c1\u8bc1\u5386\u53f2",
        "id":8505258,
        "opened":true,
        "type":0
    },
    {
        "filter":"\u5386\u53f2\u89c1\u8bc1\u4eba",
        "id":8505262,
        "opened":true,
        "type":0
    },
    {
        "filter":"^\u4f18\u96c5.*\u4f18\u96c5.*",
        "id":8505706,
        "opened":true,
        "type":1
    },
    {
        "filter":"(.{1,})\\1{1,}",
        "id":8505802,
        "opened":true,
        "type":1
    },
    {
        "filter":".*\u7684\u5440(!){0}$",
        "id":8505806,
        "opened":true,
        "type":1
    },
    {
        "filter":"\u597d\u53ef\u7231",
        "id":8505810,
        "opened":true,
        "type":0
    },
    {
        "filter":"\u53ef\u7231",
        "id":8505814,
        "opened":true,
        "type":0
    },
    {
        "filter":"\u60f3\u54ed\u554a",
        "id":8505817,
        "opened":true,
        "type":0
    },
    {
        "filter":"3871c04b",
        "id":8505823,
        "opened":true,
        "type":2
    },
    {
        "filter":"d315b53d",
        "id":8505824,
        "opened":true,
        "type":2
    },
    {
        "filter":"d5a21c74",
        "id":8505826,
        "opened":true,
        "type":2
    },
    {
        "filter":"36e2e177",
        "id":8505827,
        "opened":true,
        "type":2
    },
    {
        "filter":"\u827e\u5c14\u767b\u6cd5\u73af",
        "id":8505833,
        "opened":true,
        "type":0
    },
    {
        "filter":"\u5fc3\u75bc",
        "id":8505841,
        "opened":true,
        "type":0
    }
]